talking_data/__init__.py
talking_data/main.py
talkingdata-1.0.0.dist-info/METADATA
talkingdata-1.0.0.dist-info/WHEEL
talkingdata-1.0.0.dist-info/top_level.txt
talkingdata-1.0.0.dist-info/RECORD
