Metadata-Version: 2.4
Name: talkingdata
Version: 1.0.0
Summary: A lightweight, multi-provider AI Data Analysis library using SQL reasoning on pandas DataFrames.
Home-page: https://mabdullah40.github.io/Open-Analysis/
Author: Mohammad Abdullah
Author-email: mabdullaha407@gmail.com
Requires-Dist: pandas
Requires-Dist: duckdb
Requires-Dist: html2text
Requires-Dist: python-dotenv
Requires-Dist: streamlit
Provides-Extra: groq
Requires-Dist: groq; extra == "groq"
Provides-Extra: gemini
Requires-Dist: google-genai; extra == "gemini"
Provides-Extra: openai
Requires-Dist: openai; extra == "openai"
Dynamic: author
Dynamic: author-email
Dynamic: description
Dynamic: description-content-type
Dynamic: home-page
Dynamic: provides-extra
Dynamic: requires-dist
Dynamic: summary
